nichirin/__init__.py
nichirin/crawler.py
nichirin/pipeline.py
nichirin/confs/app.yaml
nichirin/data_pipeline/generate_embeddings.py
nichirin/data_pipeline/split.py
nichirin/retriever/solr.py
nichirin/retriever/solr_index_docs.py
nichirin/scripts/create_core.py
nichirin/scripts/data_partition.py
nichirin/scripts/install_solr.py
nichirin/scripts/seed_urls.py
nichirin/serve/__init__.py
nichirin/serve/app.py
nichirin/utils/data_utils.py
nichirin-0.0.1.dist-info/LICENSE.txt
nichirin-0.0.1.dist-info/METADATA
nichirin-0.0.1.dist-info/WHEEL
nichirin-0.0.1.dist-info/entry_points.txt
nichirin-0.0.1.dist-info/top_level.txt
nichirin-0.0.1.dist-info/RECORD
