Metadata-Version: 2.1
Name: nichirin
Version: 0.0.1
Summary: TODO
Author-email: Shivani Gowda KS <shivanigowdaks@gmail.com>
Maintainer-email: Shivani Gowda KS <shivanigowdaks@gmail.com>
License: MIT License
Keywords: retrieval augmentation,vector database,natural language processing,machine learning,deep learning,artificial intelligence
Requires-Python: >=3.6
License-File: LICENSE.txt
Requires-Dist: torch >=2.0.1
Requires-Dist: transformers >=4.21.0
Requires-Dist: nltk >=3.8.1
Requires-Dist: pyspark >=3.5.1
